aaa1111-0.1.0.dev7.dist-info/METADATA
aaa1111-0.1.0.dev7.dist-info/WHEEL
aaa1111-0.1.0.dev7.dist-info/entry_points.txt
aaa1111-0.1.0.dev7.dist-info/licenses/LICENSE
aaa1111/__init__.py
aaa1111/__main__.py
aaa1111/__version__.py
aaa1111/client/__init__.py
aaa1111/client/action.py
aaa1111/client/extras.py
aaa1111/client/info.py
aaa1111/client/main.py
aaa1111/client/options.py
aaa1111/client/toimg.py
aaa1111/types/__init__.py
aaa1111/types/base.py
aaa1111/types/extension/__init__.py
aaa1111/types/extension/controlnet.py
aaa1111/types/extension/dynamic_thresholding.py
aaa1111/types/extension/lora_block_weight.py
aaa1111/types/extension/misc.py
aaa1111/types/extras.py
aaa1111/types/info.py
aaa1111/types/toimg.py
aaa1111/utils.py
aaa1111-0.1.0.dev7.dist-info/RECORD
